.bumpversion.cfg
CONTRIBUTING.md
LICENSE
MANIFEST.in
Makefile
README.md
pyproject.toml
setup.py
docs/Makefile
docs/conf.py
docs/index.rst
docs/make.bat
src/__init__.py
src/_version.py
src/instacaptions.py
src/transcription.py
src/insta_captions.egg-info/PKG-INFO
src/insta_captions.egg-info/SOURCES.txt
src/insta_captions.egg-info/dependency_links.txt
src/insta_captions.egg-info/requires.txt
src/insta_captions.egg-info/top_level.txt
tests/__init__.py
tests/test_instacaptions.py
tests/test_transcription.py
tests/testempty.wav
tests/testempty16.wav