Metadata-Version: 2.1
Name: insta-captions
Version: 0.2.0
Summary: insta-captions is a tool that will allow for the instant transcription and translation of audio files to and from different languages.
Author-email: davidcendejas <david.cendejas@columbia.edu>
License: MIT License
Project-URL: repository, https://github.com/DavidCendejas/insta-captions
Classifier: Development Status :: 2 - Pre-Alpha
Classifier: Programming Language :: Python :: Implementation :: CPython
Classifier: Programming Language :: Python :: Implementation :: PyPy
Classifier: Programming Language :: Python :: 3
Classifier: Programming Language :: Python :: 3.7
Requires-Python: >=3.7
Provides-Extra: develop
License-File: LICENSE
